fastervit/__init__.py
fastervit/tensorboard.py
fastervit/train.py
fastervit/validate.py
fastervit/validate_pip_model.py
fastervit/assets/hierarchial_attn.png
fastervit/models/__init__.py
fastervit/models/faster_vit.py
fastervit/models/faster_vit_any_res.py
fastervit/models/registry.py
fastervit/scheduler/__init__.py
fastervit/scheduler/cosine_lr.py
fastervit/scheduler/multistep_lr.py
fastervit/scheduler/plateau_lr.py
fastervit/scheduler/poly_lr.py
fastervit/scheduler/scheduler.py
fastervit/scheduler/scheduler_factory.py
fastervit/scheduler/step_lr.py
fastervit/scheduler/tanh_lr.py
fastervit/utils/__init__.py
fastervit/utils/datasets.py
fastervit-1.0.0.dist-info/LICENSE
fastervit-1.0.0.dist-info/METADATA
fastervit-1.0.0.dist-info/WHEEL
fastervit-1.0.0.dist-info/top_level.txt
fastervit-1.0.0.dist-info/RECORD
