Metadata-Version: 2.1
Name: fastervit
Version: 1.0.0
Summary: FasterViT: Fast Vision Transformers with Hierarchical Attention
Home-page: https://github.com/NVlabs/FasterViT
Author: Ali Hatamizadeh
Author-email: ahatamiz123@gmail.com
License: NVIDIA Source Code License-NC
Keywords: pytorch pretrained models efficientnet mobilenetv3 mnasnet resnet vision transformer vit
Classifier: Programming Language :: Python :: 3.7
Classifier: Programming Language :: Python :: 3.8
Classifier: Programming Language :: Python :: 3.9
Classifier: Programming Language :: Python :: 3.10
Classifier: Programming Language :: Python :: 3.11
Classifier: Topic :: Scientific/Engineering :: Artificial Intelligence
Classifier: Topic :: Software Development
Classifier: Topic :: Software Development :: Libraries
Classifier: Topic :: Software Development :: Libraries :: Python Modules
Requires-Python: >=3.7
License-File: LICENSE
Requires-Dist: timm >=0.6.12
Requires-Dist: torchvision
Requires-Dist: pyyaml
